psychophysics_py-0.1.0.dist-info/METADATA
psychophysics_py-0.1.0.dist-info/WHEEL
psychophysics_py/__init__.py
psychophysics_py/psychophysics_py.pyd
psychophysics_py-0.1.0.dist-info/RECORD
